{"cameraMode":{"drawMode":0,"name":"Shaded","section":"Shading Mode"},"sceneLighting":true,"audioPlay":false,"sceneViewState":{"showFog":true,"showMaterialUpdate":false,"showSkybox":true,"showFlares":true,"showImageEffects":true,"showParticleSystems":true},"in2DMode":false,"pivot":{"x":1.169336199760437,"y":-2.21416974067688,"z":8.68957233428955},"rotation":{"x":0.1966768354177475,"y":0.05731700360774994,"z":-0.011516666039824486,"w":0.9787300825119019},"size":17.190290451049806,"orthographic":false}